{"type":"FeatureCollection","features":[{"type":"Feature","geometry":{"type":"Point","coordinates":[118.85533,25.24658]},"properties":{"province":"福建省","city":"莆田市","county":"仙游县","community":"枫亭镇","full_address":"福建省莆田市仙游县枫亭镇","info":""}},{"type":"Feature","geometry":{"type":"Point","coordinates":[118.119074,24.701542]},"properties":{"province":"福建省","city":"厦门市","county":"同安区","community":"新民镇湖里工业园以东、同明路以西、集安路以南、集贤路以北的区域","full_address":"福建省厦门市同安区新民镇湖里工业园以东、同明路以西、集安路以南、集贤路以北的区域","info":""}},{"type":"Feature","geometry":{"type":"Point","coordinates":[118.1233,24.710726]},"properties":{"province":"福建省","city":"厦门市","county":"同安区","community":"新民镇乌涂社区","full_address":"福建省厦门市同安区新民镇乌涂社区","info":""}},{"type":"Feature","geometry":{"type":"Point","coordinates":[118.105791,24.70532]},"properties":{"province":"福建省","city":"厦门市","county":"同安区","community":"新民镇西塘社区","full_address":"福建省厦门市同安区新民镇西塘社区","info":""}}]}