{"type":"FeatureCollection","features":[{"type":"Feature","geometry":{"type":"Point","coordinates":[113.580532,23.062295]},"properties":{"province":"广东省","city":"东莞市","county":"麻涌镇","community":"广州新华学院（东莞校区）","full_address":"广东省东莞市麻涌镇广州新华学院（东莞校区）","info":""}},{"type":"Feature","geometry":{"type":"Point","coordinates":[113.822176,22.65169]},"properties":{"province":"广东省","city":"深圳市","county":"宝安区","community":"福永街道下十围商住街71号新蓝天公寓","full_address":"广东省深圳市宝安区福永街道下十围商住街71号新蓝天公寓","info":""}}]}