{"type":"FeatureCollection","features":[{"type":"Feature","geometry":{"type":"Point","coordinates":[114.847075,38.021567]},"properties":{"province":"河北省","city":"石家庄市","county":"藁城区","community":"","full_address":"河北省石家庄市藁城区","info":""}},{"type":"Feature","geometry":{"type":"Point","coordinates":[126.675167,47.057328]},"properties":{"province":"黑龙江省","city":"绥化市","county":"望奎县","community":"惠七镇","full_address":"黑龙江省绥化市望奎县惠七镇","info":""}}]}