{"type":"FeatureCollection","features":[{"type":"Feature","geometry":{"type":"Point","coordinates":[108.955053,34.228959]},"properties":{"province":"陕西省","city":"西安市","county":"雁塔区","community":"小寨路街道长安中路33号长安大学校本部住宅区和北院宿舍","full_address":"陕西省西安市雁塔区小寨路街道长安中路33号长安大学校本部住宅区和北院宿舍","info":""}},{"type":"Feature","geometry":{"type":"Point","coordinates":[108.155933,21.524319]},"properties":{"province":"广西壮族自治区","city":"防城港市","county":"东兴市","community":"江平镇万尾村","full_address":"广西壮族自治区防城港市东兴市江平镇万尾村","info":""}}]}