{"type":"FeatureCollection","features":[{"type":"Feature","geometry":{"type":"Point","coordinates":[75.862814,39.375044]},"properties":{"province":"新疆维吾尔自治区","city":"喀什地区","county":"疏附县","community":"（除High风险地区外的其他乡镇）","full_address":"新疆维吾尔自治区喀什地区疏附县（除High风险地区外的其他乡镇）","info":""}}]}