{"type":"FeatureCollection","features":[{"type":"Feature","geometry":{"type":"Point","coordinates":[75.816012,39.410253]},"properties":{"province":"新疆维吾尔自治区","city":"喀什地区","county":"疏附县","community":"站敏乡","full_address":"新疆维吾尔自治区喀什地区疏附县站敏乡","info":""}},{"type":"Feature","geometry":{"type":"Point","coordinates":[75.861413,39.375007]},"properties":{"province":"新疆维吾尔自治区","city":"喀什地区","county":"疏附县","community":"托克扎克镇","full_address":"新疆维吾尔自治区喀什地区疏附县托克扎克镇","info":""}},{"type":"Feature","geometry":{"type":"Point","coordinates":[75.896336,39.407471]},"properties":{"province":"新疆维吾尔自治区","city":"喀什地区","county":"疏附县","community":"吾库萨克镇","full_address":"新疆维吾尔自治区喀什地区疏附县吾库萨克镇","info":""}},{"type":"Feature","geometry":{"type":"Point","coordinates":[77.293756,37.839705]},"properties":{"province":"新疆维吾尔自治区","city":"喀什地区","county":"叶城县","community":"萨依巴格乡","full_address":"新疆维吾尔自治区喀什地区叶城县萨依巴格乡","info":""}}]}