{"type":"FeatureCollection","features":[{"type":"Feature","geometry":{"type":"Point","coordinates":[117.680949,39.014377]},"properties":{"full_address":"天津市市辖区滨海新区滨海新区汉沽街"}},{"type":"Feature","geometry":{"type":"Point","coordinates":[117.180062,39.135443]},"properties":{"full_address":"天津市市辖区滨海新区，中心渔港冷链物流区A区和B区"}},{"type":"Feature","geometry":{"type":"Point","coordinates":[121.747835,31.189802]},"properties":{"full_address":"上海市市辖区浦东新区祝桥镇营前村"}},{"type":"Feature","geometry":{"type":"Point","coordinates":[116.242211,32.652868]},"properties":{"full_address":"安徽省阜阳市颍上县慎城镇张洋小区"}}]}