{"type":"FeatureCollection","features":[{"type":"Feature","geometry":{"type":"Point","coordinates":[87.425823,43.876052]},"properties":{"province":"新疆维吾尔自治区","city":"乌鲁木齐市","county":"头屯河区","community":"","full_address":"新疆维吾尔自治区乌鲁木齐市头屯河区","info":""}},{"type":"Feature","geometry":{"type":"Point","coordinates":[87.573916,43.843752]},"properties":{"province":"新疆维吾尔自治区","city":"乌鲁木齐市","county":"新市区","community":"","full_address":"新疆维吾尔自治区乌鲁木齐市新市区","info":""}},{"type":"Feature","geometry":{"type":"Point","coordinates":[87.642482,43.832459]},"properties":{"province":"新疆维吾尔自治区","city":"乌鲁木齐市","county":"水磨沟区","community":"","full_address":"新疆维吾尔自治区乌鲁木齐市水磨沟区","info":""}}]}