{"type":"FeatureCollection","features":[{"type":"Feature","geometry":{"type":"Point","coordinates":[118.85619,25.253952]},"properties":{"full_address":"福建省莆田市仙游县枫亭镇铺头社区"}},{"type":"Feature","geometry":{"type":"Point","coordinates":[118.868525,25.261943]},"properties":{"full_address":"福建省莆田市仙游县麟山村"}}]}