{"type":"FeatureCollection","features":[{"type":"Feature","geometry":{"type":"Point","coordinates":[118.85533,25.24658]},"properties":{"full_address":"福建省莆田市仙游县枫亭镇"}},{"type":"Feature","geometry":{"type":"Point","coordinates":[118.1233,24.710726]},"properties":{"full_address":"福建省厦门市同安区新民镇乌涂社区"}},{"type":"Feature","geometry":{"type":"Point","coordinates":[118.105791,24.70532]},"properties":{"full_address":"福建省厦门市同安区新民镇西塘社区"}}]}