{"type":"FeatureCollection","features":[{"type":"Feature","geometry":{"type":"Point","coordinates":[126.601875,45.980573]},"properties":{"full_address":"黑龙江省哈尔滨市呼兰区建设路街道"}},{"type":"Feature","geometry":{"type":"Point","coordinates":[126.486076,46.832719]},"properties":{"full_address":"黑龙江省绥化市望奎县"}},{"type":"Feature","geometry":{"type":"Point","coordinates":[114.847075,38.021567]},"properties":{"full_address":"河北省石家庄市藁城区"}},{"type":"Feature","geometry":{"type":"Point","coordinates":[121.589092,31.262037]},"properties":{"full_address":"上海市市辖区浦东新区高东镇新高苑一期小区"}}]}