{"type":"FeatureCollection","features":[{"type":"Feature","geometry":{"type":"Point","coordinates":[97.890538,23.979522]},"properties":{"full_address":"云南省德宏傣族景颇族自治州瑞丽市姐告国门社区"}},{"type":"Feature","geometry":{"type":"Point","coordinates":[97.893116,24.017899]},"properties":{"full_address":"云南省德宏傣族景颇族自治州瑞丽市大道以南）"}}]}