{"type":"FeatureCollection","features":[{"type":"Feature","geometry":{"type":"Point","coordinates":[126.486076,46.832719]},"properties":{"full_address":"黑龙江省绥化市望奎县"}},{"type":"Feature","geometry":{"type":"Point","coordinates":[114.847075,38.021567]},"properties":{"full_address":"河北省石家庄市藁城区"}}]}