{"type":"FeatureCollection","features":[{"type":"Feature","geometry":{"type":"Point","coordinates":[126.601875,45.980573]},"properties":{"province":"黑龙江省","city":"哈尔滨市","county":"呼兰区","community":"建设路街道","full_address":"黑龙江省哈尔滨市呼兰区建设路街道","info":""}},{"type":"Feature","geometry":{"type":"Point","coordinates":[126.486076,46.832719]},"properties":{"province":"黑龙江省","city":"绥化市","county":"望奎县","community":"","full_address":"黑龙江省绥化市望奎县","info":""}},{"type":"Feature","geometry":{"type":"Point","coordinates":[114.847075,38.021567]},"properties":{"province":"河北省","city":"石家庄市","county":"藁城区","community":"","full_address":"河北省石家庄市藁城区","info":""}},{"type":"Feature","geometry":{"type":"Point","coordinates":[121.589092,31.262037]},"properties":{"province":"上海市","city":"市辖区","county":"浦东新区","community":"高东镇新高苑一期小区","full_address":"上海市市辖区浦东新区高东镇新高苑一期小区","info":""}}]}