{"type":"FeatureCollection","features":[{"type":"Feature","geometry":{"type":"Point","coordinates":[117.227101,39.16467]},"properties":{"province":"天津市","city":"市辖区","county":"河北区","community":"宁园街舒园里5号楼","full_address":"天津市市辖区河北区宁园街舒园里5号楼","info":""}},{"type":"Feature","geometry":{"type":"Point","coordinates":[116.367665,40.03222]},"properties":{"province":"北京市","city":"市辖区","county":"丰台区","community":"玉泉营街道万柳园社区","full_address":"北京市市辖区丰台区玉泉营街道万柳园社区","info":""}},{"type":"Feature","geometry":{"type":"Point","coordinates":[106.439346,23.292481]},"properties":{"province":"广西壮族自治区","city":"百色市","county":"德保县","community":"都安乡伏计村陇意屯","full_address":"广西壮族自治区百色市德保县都安乡伏计村陇意屯","info":""}},{"type":"Feature","geometry":{"type":"Point","coordinates":[119.62102,40.40508]},"properties":{"province":"辽宁省","city":"葫芦岛市","county":"绥中县","community":"加碑岩乡窝岭村","full_address":"辽宁省葫芦岛市绥中县加碑岩乡窝岭村","info":""}}]}