{"type":"FeatureCollection","features":[{"type":"Feature","geometry":{"type":"Point","coordinates":[116.380637,40.173894]},"properties":{"full_address":"北京市昌平区小汤山镇大汤山村双兴苑小区"}},{"type":"Feature","geometry":{"type":"Point","coordinates":[112.670831,43.756619]},"properties":{"full_address":"内蒙古自治区锡林郭勒盟苏尼特左旗赛罕高毕苏木"}},{"type":"Feature","geometry":{"type":"Point","coordinates":[112.255635,44.681291]},"properties":{"full_address":"内蒙古自治区锡林郭勒盟苏尼特左旗洪格尔苏木"}}]}